{
  "Понедельник": [
    "&nbsp",
    "Математический анализ лекция\nХуденко В.Н.\n231",
    "Комплексный анализ практика\nВерещагина\n225",
    "Физика практика\nГорбачев А.А.\n229",
    "&nbsp",
    "Атлетическая гимнастика\n Картавый С.В.\nТренажерный зал, ул. Соммера, 23\nC 3 февраля",
    "&nbsp"
  ],
  "Вторник": [
    "ООП лекция\nВерещагин Михаил Дмитриевич\n229",
    "Физика лекция\nГорбачев А.А.\n231",
    "Комплексный анализ лекция\nВерещагина\n225",
    "&nbsp",
    "&nbsp",
    "Операционные системы и компьютерные сети\nАгафонова М.М.\nОнлайн",
    "&nbsp"
  ],
  "Среда": [
    "Дискретная математика лекция\nКащенко Н.М.\n229",
    "ООП Практика\nЛушников\n220",
    "Дискретная математика практика\nКащенко\n232",
    "Иностранный язык\nЯкубовская А.Е.\n213",
    "Иностранный язык\nЯкубовская А.Е.\n213\nВ/Н",
    "&nbsp",
    "Физическая культура\nEIOS"
  ],
  "Четверг": [
    "Дифференциальные уравнения лекция\nИшанов С.А.\n233",
    "Математический анализ практика\nКочина А.С.\n215",
    "&nbsp",
    "&nbsp",
    "&nbsp",
    "&nbsp",
    "&nbsp"
  ],
  "Пятница": [
    "Алгоритмы и структуры данных практика\nБалабанов А.В.\n230",
    "Дифференциальные уравнения практика\nИшанов С.А.\n233",
    "Алгоритмы и структуры данных лекция\nДанилин А.С.\n229",
    "&nbsp",
    "&nbsp",
    "Операционные системы и компьютерные сети\nАгафонова М.М.\nОнлайн",
    "WEB-программирование лабораторные\nКоломоец\nОнлайн  "
  ],
  "Суббота": [
    "WEB-программирование лекция\nКоломоец\nОнлайн",
    "Безопасность жизнедеятельности лекция\n\nEIOS",
    "&nbsp",
    "&nbsp",
    "&nbsp",
    "&nbsp",
    "&nbsp"
  ]
}
